automate/__init__.py
automate/요약_프롬프트.md
automate/cli/__init__.py
automate/cli/utils.py
automate/cli/commands/__init__.py
automate/cli/commands/dispatch.py
automate/cli/commands/serve.py
automate/cli/commands/telegram.py
automate/cli/commands/transcribe.py
automate/core/__init__.py
automate/core/config.py
automate/core/constants.py
automate/scripts/__init__.py
automate/scripts/get_transcript.py
automate/services/__init__.py
automate/services/airtable/__init__.py
automate/services/airtable/client.py
automate/services/airtable/repository.py
automate/services/summary/__init__.py
automate/services/summary/formatter.py
automate/services/summary/generator.py
automate/services/summary/prompt.py
automate/services/telegram/__init__.py
automate/services/telegram/bot.py
automate/services/telegram/sender.py
automate/services/telegram/webhook.py
automate/services/telegram/tasks/README.md
automate/services/telegram/tasks/__init__.py
automate/services/telegram/tasks/base.py
automate/services/telegram/tasks/shorts_task.py
automate/services/telegram/tasks/summary_task.py
automate/services/youtube/__init__.py
automate/services/youtube/extractor.py
automate/services/youtube/metadata.py
automate/services/youtube/processor.py
automate/services/youtube/transcript.py
automate/utils/__init__.py
automate/utils/async_utils.py
automate/utils/transcript_utils.py
automate/utils/youtube_utils.py
automate_youtube_summarize-0.2.10.dist-info/METADATA
automate_youtube_summarize-0.2.10.dist-info/WHEEL
automate_youtube_summarize-0.2.10.dist-info/entry_points.txt
automate_youtube_summarize-0.2.10.dist-info/RECORD
