Metadata-Version: 2.4
Name: automate-youtube-summarize
Version: 0.2.10
Summary: YouTube 영상 대본 추출, AI 요약, Airtable 저장 및 텔레그램 봇 기능을 제공하는 자동화 도구
Project-URL: Homepage, https://github.com/hakunamta00700/automate
Project-URL: Repository, https://github.com/hakunamta00700/automate
Project-URL: Issues, https://github.com/hakunamta00700/automate/issues
Author-email: David Cho <csi00700@gmail.com>
License: MIT
Keywords: ai,airtable,automation,bot,gemini,openai,summarization,telegram,transcript,youtube
Classifier: Development Status :: 4 - Beta
Classifier: Intended Audience :: Developers
Classifier: License :: OSI Approved :: MIT License
Classifier: Operating System :: OS Independent
Classifier: Programming Language :: Python
Classifier: Programming Language :: Python :: 3
Classifier: Programming Language :: Python :: 3.12
Classifier: Topic :: Communications :: Chat
Classifier: Topic :: Internet :: WWW/HTTP :: Dynamic Content
Classifier: Topic :: Multimedia :: Video
Classifier: Topic :: Software Development :: Libraries :: Python Modules
Requires-Python: >=3.12
Requires-Dist: aiohttp>=3.9.3
Requires-Dist: bs4>=0.0.2
Requires-Dist: click>=8.1.8
Requires-Dist: fastapi>=0.115.12
Requires-Dist: google-genai>=1.14.0
Requires-Dist: hypercorn>=0.17.3
Requires-Dist: loguru>=0.7.3
Requires-Dist: openai>=1.78.0
Requires-Dist: pyairtable>=3.1.1
Requires-Dist: python-dotenv>=1.1.0
Requires-Dist: python-telegram-bot[ext]>=22.0
Requires-Dist: pyzmq>=26.4.0
Requires-Dist: tqdm>=4.67.1
Requires-Dist: uv-easy>=0.2.5
Requires-Dist: youtube-transcript-api==1.2.3
Provides-Extra: dev
Requires-Dist: autoflake>=2.3.1; extra == 'dev'
Requires-Dist: autopep8>=2.3.2; extra == 'dev'
Requires-Dist: black>=25.1.0; extra == 'dev'
Requires-Dist: isort>=6.0.1; extra == 'dev'
